Metadata-Version: 1.1
Name: python-kubernetes
Version: 0.2
Summary: A Python wrapper around the Kubernetes API
Home-page: https://github.com/cosmos-io/python-kubernetes
Author: pjs7678
Author-email: pjs7678@cosmos.io
License: Apache License 2.0
Keywords: kubernetes api
Platform: UNKNOWN
Classifier: Development Status :: 5 - Production/Stable
Classifier: Intended Audience :: Developers
Classifier: License :: OSI Approved :: Apache Software License
Classifier: Operating System :: OS Independent
Classifier: Topic :: Software Development :: Libraries :: Python Modules
Classifier: Topic :: Communications :: Chat
Classifier: Topic :: Internet
Classifier: Programming Language :: Python
Classifier: Programming Language :: Python :: 2
Classifier: Programming Language :: Python :: 2.7
